setup.py
bin/ims
ims/__init__.py
ims.egg-info/PKG-INFO
ims.egg-info/SOURCES.txt
ims.egg-info/dependency_links.txt
ims.egg-info/not-zip-safe
ims.egg-info/requires.txt
ims.egg-info/top_level.txt