Metadata-Version: 1.0
Name: ims
Version: 3.3
Summary: Instantly stream movies/ tv episodes
Home-page: http://iyask.me
Author: Yask Srivastava
Author-email: yask123@gmail.com
License: MIT
Platform: UNKNOWN
